nodekind.cpython-310-darwin.so
saxonc.cpython-310-darwin.so
saxonpy/__init__.py
saxonpy/saxonc_home/libsaxonhec.dylib
saxonpy/saxonc_home/rt/lib/calendars.properties
saxonpy/saxonc_home/rt/lib/charsets.jar
saxonpy/saxonc_home/rt/lib/content-types.properties
saxonpy/saxonc_home/rt/lib/currency.data
saxonpy/saxonc_home/rt/lib/flavormap.properties
saxonpy/saxonc_home/rt/lib/fontconfig.bfc
saxonpy/saxonc_home/rt/lib/fontconfig.properties.src
saxonpy/saxonc_home/rt/lib/hijrah-config-umalqura.properties
saxonpy/saxonc_home/rt/lib/jce.jar
saxonpy/saxonc_home/rt/lib/jspawnhelper
saxonpy/saxonc_home/rt/lib/jsse.jar
saxonpy/saxonc_home/rt/lib/jvm.cfg
saxonpy/saxonc_home/rt/lib/libAppleScriptEngine.dylib
saxonpy/saxonc_home/rt/lib/libawt.dylib
saxonpy/saxonc_home/rt/lib/libawt_lwawt.dylib
saxonpy/saxonc_home/rt/lib/libfontmanager.dylib
saxonpy/saxonc_home/rt/lib/libfreetype.dylib
saxonpy/saxonc_home/rt/lib/libj2gss.dylib
saxonpy/saxonc_home/rt/lib/libj2pcsc.dylib
saxonpy/saxonc_home/rt/lib/libj2pkcs11.dylib
saxonpy/saxonc_home/rt/lib/libjaas_unix.dylib
saxonpy/saxonc_home/rt/lib/libjava.dylib
saxonpy/saxonc_home/rt/lib/libjawt.dylib
saxonpy/saxonc_home/rt/lib/libjpeg.dylib
saxonpy/saxonc_home/rt/lib/libjsound.dylib
saxonpy/saxonc_home/rt/lib/libjvm.dylib
saxonpy/saxonc_home/rt/lib/liblcms.dylib
saxonpy/saxonc_home/rt/lib/libmlib_image.dylib
saxonpy/saxonc_home/rt/lib/libnet.dylib
saxonpy/saxonc_home/rt/lib/libnio.dylib
saxonpy/saxonc_home/rt/lib/libosx.dylib
saxonpy/saxonc_home/rt/lib/libosxapp.dylib
saxonpy/saxonc_home/rt/lib/libosxkrb5.dylib
saxonpy/saxonc_home/rt/lib/libosxui.dylib
saxonpy/saxonc_home/rt/lib/libsunec.dylib
saxonpy/saxonc_home/rt/lib/libunpack.dylib
saxonpy/saxonc_home/rt/lib/libzip.dylib
saxonpy/saxonc_home/rt/lib/locales
saxonpy/saxonc_home/rt/lib/logging.properties
saxonpy/saxonc_home/rt/lib/meta-index
saxonpy/saxonc_home/rt/lib/net.properties
saxonpy/saxonc_home/rt/lib/psfont.properties.ja
saxonpy/saxonc_home/rt/lib/psfontj2d.properties
saxonpy-0.0.3.dist-info/METADATA
saxonpy-0.0.3.dist-info/WHEEL
saxonpy-0.0.3.dist-info/top_level.txt
saxonpy-0.0.3.dist-info/RECORD
