Metadata-Version: 2.1
Name: saxonpy
Version: 0.0.3
Summary: A python package for the Saxon/C 1.2.1, an XML processor by Saxonica.
Home-page: https://github.com/tennom/saxonpy
Author: Tennom
Author-email: tennom@outlook.com
License: UNKNOWN
Platform: UNKNOWN
Requires-Python: >=3.6
